README.md
setup.cfg
setup.py
django_github_s3.egg-info/PKG-INFO
django_github_s3.egg-info/SOURCES.txt
django_github_s3.egg-info/dependency_links.txt
django_github_s3.egg-info/not-zip-safe
django_github_s3.egg-info/requires.txt
django_github_s3.egg-info/top_level.txt
github_storages/__init__.py
github_storages/admin.py
github_storages/apps.py
github_storages/backend.py
github_storages/utils.py